{"type":"object","properties":{"title":{"type":"string","minLength":1,"maxLength":200,"description":"Updated job title (max 200 chars)."},"company":{"type":"string","minLength":1,"maxLength":200,"description":"Updated hiring company name (max 200 chars)."},"location":{"type":"string","maxLength":200,"description":"Updated location label. Optional."},"jobType":{"type":"string","enum":["INTERNSHIP","CONTRACT","FULL_TIME","PART_TIME","VOLUNTEER","FREELANCE"],"description":"Updated employment type."},"description":{"type":"string","minLength":1,"description":"Updated long-form job description."},"requirements":{"type":"array","items":{"type":"string","maxLength":200},"maxItems":40,"description":"Updated list of required qualifications."},"skills":{"type":"array","items":{"type":"string","maxLength":60},"maxItems":40,"description":"Updated list of relevant skills."},"salaryRange":{"type":"string","maxLength":100,"description":"Updated free-form salary range label."},"applyUrl":{"allOf":[{"type":"string","maxLength":500,"format":"uri","pattern":"^https?:\\/\\/","description":"External URL recruiters share with candidates to apply. Optional.","example":"https://fixture.profile.local","x-readme-ref-name":"SocialUrl"},{"description":"Updated external apply URL. Optional."}]},"isActive":{"type":"boolean","description":"Whether the job is currently active and visible."},"expiresAt":{"type":"string","format":"date-time","description":"ISO-8601 timestamp with timezone offset (RFC 3339).","example":"2026-05-07T00:00:00.000Z"},"paymentCurrency":{"type":"string","nullable":true,"enum":["BRL","USD","EUR","GBP"],"description":"Updated ISO 4217 currency code. Null clears the previous value."},"remotePolicy":{"type":"string","nullable":true,"enum":["REMOTE","HYBRID","ONSITE"],"description":"Updated remote / hybrid / on-site policy. Null clears the previous value."},"minEnglishLevel":{"type":"string","nullable":true,"enum":["BASIC","INTERMEDIATE","ADVANCED","FLUENT"],"description":"Updated minimum English level. Null clears the previous value."}},"description":"Partial update of a job. Nullable enums let users clear an existing selection.","example":{"title":"Senior Backend Engineer (Updated)","isActive":true},"x-readme-ref-name":"UpdateJobRequest"}